neon_solver_wordnet_plugin/__init__.py
neon_solver_wordnet_plugin-0.0.2a0.dist-info/METADATA
neon_solver_wordnet_plugin-0.0.2a0.dist-info/WHEEL
neon_solver_wordnet_plugin-0.0.2a0.dist-info/entry_points.txt
neon_solver_wordnet_plugin-0.0.2a0.dist-info/top_level.txt
neon_solver_wordnet_plugin-0.0.2a0.dist-info/zip-safe
neon_solver_wordnet_plugin-0.0.2a0.dist-info/RECORD
