Metadata-Version: 2.1
Name: neon-solver-wordnet-plugin
Version: 0.0.2a0
Summary: A question solver plugin for ovos/neon/mycroft
Home-page: https://github.com/NeonGeckoCom/neon_solver_wordnet_plugin
Author: Neongecko
Author-email: developers@neon.ai
License: bsd3
Keywords: mycroft plugin utterance fallback query
Platform: UNKNOWN
Requires-Dist: simplematch
Requires-Dist: nltk
